Data_Split_by_Bhawika/split_train_validation.py
Data_Split-1.0.0.dist-info/LICENSE.txt
Data_Split-1.0.0.dist-info/METADATA
Data_Split-1.0.0.dist-info/WHEEL
Data_Split-1.0.0.dist-info/entry_points.txt
Data_Split-1.0.0.dist-info/top_level.txt
Data_Split-1.0.0.dist-info/RECORD
