Metadata-Version: 2.1
Name: Data-Split
Version: 1.0.0
Summary: A python package to split Directory into Training, Testing and Validation Directory
Home-page: https://github.com/Bhawika16/Data_Split
Author: BHAWIKA ARORA
Author-email: bhawikavk2@gmail.com
License: MIT
Platform: UNKNOWN
Classifier: License :: OSI Approved :: MIT License
Classifier: Programming Language :: Python :: 3
Classifier: Programming Language :: Python :: 3.4
Classifier: Programming Language :: Python :: 3.5
Classifier: Programming Language :: Python :: 3.6
Classifier: Programming Language :: Python :: 3.7
